talipp/__init__.py
talipp/exceptions.py
talipp/indicator_util.py
talipp/input.py
talipp/ma.py
talipp/ohlcv.py
talipp/indicators/ADX.py
talipp/indicators/ALMA.py
talipp/indicators/AO.py
talipp/indicators/ATR.py
talipp/indicators/AccuDist.py
talipp/indicators/Aroon.py
talipp/indicators/BB.py
talipp/indicators/BOP.py
talipp/indicators/CCI.py
talipp/indicators/CHOP.py
talipp/indicators/ChaikinOsc.py
talipp/indicators/ChandeKrollStop.py
talipp/indicators/CoppockCurve.py
talipp/indicators/DEMA.py
talipp/indicators/DPO.py
talipp/indicators/DonchianChannels.py
talipp/indicators/EMA.py
talipp/indicators/EMV.py
talipp/indicators/FibonacciRetracement.py
talipp/indicators/ForceIndex.py
talipp/indicators/HMA.py
talipp/indicators/IBS.py
talipp/indicators/Ichimoku.py
talipp/indicators/Indicator.py
talipp/indicators/KAMA.py
talipp/indicators/KST.py
talipp/indicators/KVO.py
talipp/indicators/KeltnerChannels.py
talipp/indicators/MACD.py
talipp/indicators/MassIndex.py
talipp/indicators/McGinleyDynamic.py
talipp/indicators/MeanDev.py
talipp/indicators/NATR.py
talipp/indicators/OBV.py
talipp/indicators/ParabolicSAR.py
talipp/indicators/PivotsHL.py
talipp/indicators/ROC.py
talipp/indicators/RSI.py
talipp/indicators/RogersSatchell.py
talipp/indicators/SFX.py
talipp/indicators/SMA.py
talipp/indicators/SMMA.py
talipp/indicators/SOBV.py
talipp/indicators/STC.py
talipp/indicators/StdDev.py
talipp/indicators/Stoch.py
talipp/indicators/StochRSI.py
talipp/indicators/SuperTrend.py
talipp/indicators/T3.py
talipp/indicators/TEMA.py
talipp/indicators/TRIX.py
talipp/indicators/TSI.py
talipp/indicators/TTM.py
talipp/indicators/UO.py
talipp/indicators/VTX.py
talipp/indicators/VWAP.py
talipp/indicators/VWMA.py
talipp/indicators/WMA.py
talipp/indicators/Williams.py
talipp/indicators/ZLEMA.py
talipp/indicators/ZigZag.py
talipp/indicators/__init__.py
talipp-2.7.0.dist-info/LICENSE
talipp-2.7.0.dist-info/METADATA
talipp-2.7.0.dist-info/WHEEL
talipp-2.7.0.dist-info/top_level.txt
talipp-2.7.0.dist-info/RECORD
